jiofiber/__init__.py
jiofiber/jioFiberAPI.py
jiofiber/jiofiber.py
jioFiber_Api-0.1.7.dist-info/LICENSE.txt
jioFiber_Api-0.1.7.dist-info/METADATA
jioFiber_Api-0.1.7.dist-info/WHEEL
jioFiber_Api-0.1.7.dist-info/top_level.txt
jioFiber_Api-0.1.7.dist-info/RECORD
