Metadata-Version: 2.1
Name: jioFiber-Api
Version: 0.1.7
Summary: Unoffical JioFiber Router API to access it via python
Home-page: http://github.com/shreyaskapale/jiofiber-api
Author: Shreyas Kapale
Author-email: kapale.shreyas@gmail.com
License: MIT
Platform: UNKNOWN
Classifier: License :: OSI Approved :: MIT License
Classifier: Programming Language :: Python
Requires-Python: >=3.6.0
Requires-Dist: beautifulsoup4
Requires-Dist: requests
